apoastro/__init__.py
apoastro/keplerian_elements.py
apoastro/numerical_solution.py
apoastro/utils.py
apoastro-1.0.1.dist-info/METADATA
apoastro-1.0.1.dist-info/WHEEL
apoastro-1.0.1.dist-info/top_level.txt
apoastro-1.0.1.dist-info/RECORD
