Metadata-Version: 2.1
Name: apoastro
Version: 1.0.1
Summary: two-body and n-body problem
Home-page: https://github.com/clnrp/apoastro
Author: Cleoner Pietralonga
Author-email: cleonerp@gmail.com
License: UNKNOWN
Platform: UNKNOWN
Classifier: Development Status :: 4 - Beta
Classifier: Intended Audience :: Science/Research
Classifier: Topic :: Scientific/Engineering
Classifier: License :: OSI Approved :: Apache Software License
Classifier: Programming Language :: Python :: 2.7
Classifier: Programming Language :: Python :: 3
Classifier: Programming Language :: Python :: 3.4
Classifier: Programming Language :: Python :: 3.5
Requires-Dist: numpy
